bbknn/__init__.py
bbknn/matrix.py
bbknn-1.6.0.dist-info/LICENSE
bbknn-1.6.0.dist-info/WHEEL
bbknn-1.6.0.dist-info/METADATA
bbknn-1.6.0.dist-info/RECORD
