Metadata-Version: 2.1
Name: bbknn
Version: 1.6.0
Summary: Batch balanced KNN
Author-email: "Krzysztof Polanski, Jongeun Park" <kp9@sanger.ac.uk>
Requires-Python: >=3.7
Classifier: License :: OSI Approved :: MIT License
Requires-Dist: Cython
Requires-Dist: scipy>=1.6.0
Requires-Dist: numpy
Requires-Dist: pandas
Requires-Dist: annoy
Requires-Dist: pynndescent
Requires-Dist: umap-learn
Requires-Dist: scikit-learn>=1.0.2
Project-URL: Documentation, https://bbknn.readthedocs.io/en/latest/
Project-URL: Home, https://github.com/Teichlab/bbknn
